scippnexus/__init__.py
scippnexus/_cache.py
scippnexus/_common.py
scippnexus/_load.py
scippnexus/_string.py
scippnexus/attrs.py
scippnexus/base.py
scippnexus/event_field.py
scippnexus/field.py
scippnexus/file.py
scippnexus/nexus_classes.py
scippnexus/nxcylindrical_geometry.py
scippnexus/nxdata.py
scippnexus/nxdetector.py
scippnexus/nxevent_data.py
scippnexus/nxlog.py
scippnexus/nxmonitor.py
scippnexus/nxoff_geometry.py
scippnexus/nxsample.py
scippnexus/nxtransformations.py
scippnexus/py.typed
scippnexus/typing.py
scippnexus/application_definitions/nxcansas/__init__.py
scippnexus/application_definitions/nxcansas/nxcansas.py
scippnexus/data/__init__.py
scippnexus/docs/our-interpretation-of-the-nexus-format.md
scippnexus-26.1.0.dist-info/licenses/LICENSE
scippnexus-26.1.0.dist-info/METADATA
scippnexus-26.1.0.dist-info/WHEEL
scippnexus-26.1.0.dist-info/top_level.txt
scippnexus-26.1.0.dist-info/RECORD
