Metadata-Version: 2.4
Name: scippnexus
Version: 26.1.0
Summary: An h5py-like utility for NeXus files with seamless Scipp integration
Author: Scipp contributors
License-Expression: BSD-3-Clause
Project-URL: Bug Tracker, https://github.com/scipp/scippnexus/issues
Project-URL: Documentation, https://scipp.github.io/scippnexus
Project-URL: Source, https://github.com/scipp/scippnexus
Classifier: Intended Audience :: Science/Research
Classifier: Natural Language :: English
Classifier: Operating System :: OS Independent
Classifier: Programming Language :: Python :: 3
Classifier: Programming Language :: Python :: 3 :: Only
Classifier: Programming Language :: Python :: 3.11
Classifier: Programming Language :: Python :: 3.12
Classifier: Programming Language :: Python :: 3.13
Classifier: Topic :: Scientific/Engineering
Classifier: Typing :: Typed
Requires-Python: >=3.11
License-File: LICENSE
Requires-Dist: scipp>=24.02.0
Requires-Dist: scipy>=1.10.0
Requires-Dist: h5py>=3.12
Provides-Extra: test
Requires-Dist: pytest>=7.0; extra == "test"
Dynamic: license-file
